LICENSE
MANIFEST.in
README.md
pyproject.toml
requirements.txt
amid/__init__.py
amid/__version__.py
amid/bimcv.py
amid/brats2021.py
amid/cl_detection.py
amid/covid_1110.py
amid/crlm.py
amid/crossmoda.py
amid/ct_ich.py
amid/curvas.py
amid/deeplesion.py
amid/egd.py
amid/flare2022.py
amid/hcp.py
amid/kits.py
amid/liver_medseg.py
amid/luna25.py
amid/medseg9.py
amid/midrc.py
amid/mood.py
amid/msd.py
amid/nlst.py
amid/nsclc.py
amid/stanford_coca.py
amid/tbad.py
amid/transforms.py
amid/utils.py
amid/verse.py
amid.egg-info/PKG-INFO
amid.egg-info/SOURCES.txt
amid.egg-info/dependency_links.txt
amid.egg-info/requires.txt
amid.egg-info/top_level.txt
amid/amos/__init__.py
amid/amos/dataset.py
amid/cancer_500/__init__.py
amid/cancer_500/dataset.py
amid/cancer_500/nodules.py
amid/cancer_500/typing.py
amid/cc359/__init__.py
amid/cc359/dataset.py
amid/cc359/transforms.py
amid/internals/__init__.py
amid/internals/dataset.py
amid/internals/licenses.py
amid/internals/registry.py
amid/lidc/__init__.py
amid/lidc/dataset.py
amid/lidc/nodules.py
amid/lidc/transforms.py
amid/lidc/typing.py
amid/lits/__init__.py
amid/lits/dataset.py
amid/lits/transforms.py
amid/mslub/__init__.py
amid/mslub/dataset.py
amid/ribfrac/__init__.py
amid/ribfrac/dataset.py
amid/rsna_bc/__init__.py
amid/rsna_bc/dataset.py
amid/rsna_bc/utils.py
amid/totalsegmentator/__init__.py
amid/totalsegmentator/const.py
amid/totalsegmentator/dataset.py
amid/totalsegmentator/utils.py
amid/upenn_gbm/__init__.py
amid/upenn_gbm/data_classes.py
amid/upenn_gbm/upenn_gbm.py
amid/vs_seg/__init__.py
amid/vs_seg/dataset.py
amid/vs_seg/transforms.py
tests/test_consistency.py