Metadata-Version: 2.4
Name: amid
Version: 0.15.0
Summary: A curated list of medical imaging datasets with unified interfaces
Author-email: NeuroML Group <max@ira-labs.com>
License: MIT License
Project-URL: Homepage, https://github.com/neuro-ml/amid
Project-URL: Issues, https://github.com/neuro-ml/amid/issues
Project-URL: Source, https://github.com/neuro-ml/amid
Project-URL: Docs, https://neuro-ml.github.io/amid
Keywords: medical imaging,dataset
Classifier: Development Status :: 4 - Beta
Classifier: License :: OSI Approved :: MIT License
Classifier: Programming Language :: Python :: 3
Classifier: Programming Language :: Python :: 3.8
Classifier: Programming Language :: Python :: 3.9
Classifier: Programming Language :: Python :: 3.10
Classifier: Programming Language :: Python :: 3.11
Classifier: Programming Language :: Python :: 3 :: Only
Requires-Python: >=3.8
License-File: LICENSE
Requires-Dist: connectome<1.0.0,>=0.10.0
Requires-Dist: numpy
Requires-Dist: nibabel
Requires-Dist: more-itertools
Requires-Dist: dicom-csv
Requires-Dist: tqdm
Requires-Dist: pandas
Requires-Dist: pylidc
Requires-Dist: joblib
Requires-Dist: deli<1.0.0
Requires-Dist: scipy
Requires-Dist: scikit-image
Requires-Dist: pydicom
Requires-Dist: imops
Requires-Dist: highdicom
Requires-Dist: SimpleITK
Dynamic: license-file
